[
  {
    "date": "2025-11-01",
    "httpErrorNon5xx": 19623,
    "httpError5xx": 0,
    "socketHangUpErrors": 1328,
    "successfulOrders": 2840,
    "failedOrders": 11,
    "successfulMobilePayments": 66,
    "failedMobilePayments": 6,
    "successfulPaypalButFailedSubmitOrder": 2,
    "failedMobilePaypal": 2,
    "openCheck": 115,
    "totalEapis": 148744,
    "cronjobEapis": 27910,
    "eapiDurationOver10Seconds": 908,
    "successfulDesktopPayments": 2738,
    "failedDesktopPayments": 423,
    "successfulPaypal": 257,
    "failedDesktopPaypal": 35
  },
  {
    "date": "2025-11-02",
    "totalEapis": 157027,
    "httpErrorNon5xx": 19369,
    "httpError5xx": 0,
    "socketHangUpErrors": 1540,
    "cronjobEapis": 47971,
    "eapiDurationOver10Seconds": 700,
    "successfulOrders": 2517,
    "failedOrders": 1,
    "successfulMobilePayments": 81,
    "failedMobilePayments": 7,
    "successfulDesktopPayments": 2413,
    "failedDesktopPayments": 357,
    "successfulPaypalButFailedSubmitOrder": 1,
    "successfulPaypal": 220,
    "failedMobilePaypal": 2,
    "failedDesktopPaypal": 19,
    "openCheck": 115
  },
  {
    "date": "2025-11-03",
    "totalEapis": 146767,
    "httpErrorNon5xx": 16954,
    "httpError5xx": 0,
    "socketHangUpErrors": 1486,
    "cronjobEapis": 45558,
    "eapiDurationOver10Seconds": 1016,
    "successfulOrders": 2529,
    "failedOrders": 133,
    "successfulMobilePayments": 47,
    "failedMobilePayments": 2,
    "successfulDesktopPayments": 2430,
    "failedDesktopPayments": 358,
    "successfulPaypalButFailedSubmitOrder": 7,
    "successfulPaypal": 238,
    "failedMobilePaypal": 0,
    "failedDesktopPaypal": 26,
    "openCheck": 118
  },
  {
    "date": "2025-11-04",
    "totalEapis": 162959,
    "httpErrorNon5xx": 17896,
    "httpError5xx": 0,
    "socketHangUpErrors": 1434,
    "cronjobEapis": 46701,
    "eapiDurationOver10Seconds": 771,
    "successfulOrders": 3327,
    "failedOrders": 11,
    "successfulMobilePayments": 147,
    "failedMobilePayments": 12,
    "successfulDesktopPayments": 3293,
    "failedDesktopPayments": 476,
    "successfulPaypalButFailedSubmitOrder": 1,
    "successfulPaypal": 224,
    "failedMobilePaypal": 0,
    "failedDesktopPaypal": 22,
    "openCheck": 236
  },
  {
    "date": "2025-11-05",
    "totalEapis": 153772,
    "httpErrorNon5xx": 17932,
    "httpError5xx": 0,
    "socketHangUpErrors": 1523,
    "cronjobEapis": 46126,
    "eapiDurationOver10Seconds": 808,
    "successfulOrders": 2797,
    "failedOrders": 6,
    "successfulMobilePayments": 58,
    "failedMobilePayments": 0,
    "successfulDesktopPayments": 2707,
    "failedDesktopPayments": 367,
    "successfulPaypalButFailedSubmitOrder": 0,
    "successfulPaypal": 220,
    "failedMobilePaypal": 0,
    "failedDesktopPaypal": 21,
    "openCheck": 117
  },
  {
    "date": "2025-11-06",
    "totalEapis": 167565,
    "httpErrorNon5xx": 20291,
    "httpError5xx": 3,
    "socketHangUpErrors": 1615,
    "cronjobEapis": 49371,
    "eapiDurationOver10Seconds": 1421,
    "successfulOrders": 2910,
    "failedOrders": 12,
    "successfulMobilePayments": 88,
    "failedMobilePayments": 1,
    "successfulDesktopPayments": 2803,
    "failedDesktopPayments": 353,
    "successfulPaypalButFailedSubmitOrder": 0,
    "successfulPaypal": 206,
    "failedMobilePaypal": 0,
    "failedDesktopPaypal": 15,
    "openCheck": 139
  },
  {
    "date": "2025-11-07",
    "totalEapis": 238447,
    "httpErrorNon5xx": 29463,
    "httpError5xx": 162,
    "socketHangUpErrors": 1976,
    "cronjobEapis": 73801,
    "eapiDurationOver10Seconds": 2973,
    "successfulOrders": 3506,
    "failedOrders": 21,
    "successfulMobilePayments": 104,
    "failedMobilePayments": 5,
    "successfulDesktopPayments": 3400,
    "failedDesktopPayments": 483,
    "successfulPaypalButFailedSubmitOrder": 1,
    "successfulPaypal": 333,
    "failedMobilePaypal": 0,
    "failedDesktopPaypal": 37,
    "openCheck": 157
  },
  {
    "date": "2025-11-08",
    "totalEapis": 200412,
    "httpErrorNon5xx": 25243,
    "httpError5xx": 46,
    "socketHangUpErrors": 1701,
    "cronjobEapis": 54834,
    "eapiDurationOver10Seconds": 999,
    "successfulOrders": 3137,
    "failedOrders": 4,
    "successfulMobilePayments": 111,
    "failedMobilePayments": 14,
    "successfulDesktopPayments": 3003,
    "failedDesktopPayments": 368,
    "successfulPaypalButFailedSubmitOrder": 1,
    "successfulPaypal": 254,
    "failedMobilePaypal": 0,
    "failedDesktopPaypal": 19,
    "openCheck": 184
  },
  {
    "date": "2025-11-09",
    "totalEapis": 167368,
    "httpErrorNon5xx": 20705,
    "httpError5xx": 32,
    "socketHangUpErrors": 1478,
    "cronjobEapis": 48188,
    "eapiDurationOver10Seconds": 636,
    "successfulOrders": 2653,
    "failedOrders": 4,
    "successfulMobilePayments": 81,
    "failedMobilePayments": 16,
    "successfulDesktopPayments": 2549,
    "failedDesktopPayments": 327,
    "successfulPaypalButFailedSubmitOrder": 1,
    "successfulPaypal": 289,
    "failedMobilePaypal": 0,
    "failedDesktopPaypal": 20,
    "openCheck": 153
  },
  {
    "date": "2025-11-10",
    "totalEapis": 162889,
    "httpErrorNon5xx": 19472,
    "httpError5xx": 0,
    "socketHangUpErrors": 1575,
    "cronjobEapis": 47016,
    "eapiDurationOver10Seconds": 615,
    "successfulOrders": 2769,
    "failedOrders": 3,
    "successfulMobilePayments": 110,
    "failedMobilePayments": 7,
    "successfulDesktopPayments": 2667,
    "failedDesktopPayments": 363,
    "successfulPaypalButFailedSubmitOrder": 0,
    "successfulPaypal": 239,
    "failedMobilePaypal": 1,
    "failedDesktopPaypal": 17,
    "openCheck": 187
  },
  {
    "date": "2025-11-11",
    "totalEapis": 215728,
    "httpErrorNon5xx": 25806,
    "httpError5xx": 0,
    "socketHangUpErrors": 1904,
    "cronjobEapis": 56795,
    "eapiDurationOver10Seconds": 581,
    "successfulOrders": 3964,
    "failedOrders": 6,
    "successfulMobilePayments": 192,
    "failedMobilePayments": 7,
    "successfulDesktopPayments": 3922,
    "failedDesktopPayments": 499,
    "successfulPaypalButFailedSubmitOrder": 2,
    "successfulPaypal": 283,
    "failedMobilePaypal": 1,
    "failedDesktopPaypal": 31,
    "openCheck": 356
  },
  {
    "date": "2025-11-12",
    "totalEapis": 156919,
    "httpErrorNon5xx": 18701,
    "httpError5xx": 0,
    "socketHangUpErrors": 1389,
    "cronjobEapis": 45652,
    "eapiDurationOver10Seconds": 519,
    "successfulOrders": 2718,
    "failedOrders": 4,
    "successfulMobilePayments": 108,
    "failedMobilePayments": 2,
    "successfulDesktopPayments": 2589,
    "failedDesktopPayments": 365,
    "successfulPaypalButFailedSubmitOrder": 0,
    "successfulPaypal": 234,
    "failedMobilePaypal": 1,
    "failedDesktopPaypal": 21,
    "openCheck": 167
  },
  {
    "date": "2025-11-14",
    "totalEapis": 214131,
    "httpErrorNon5xx": 25449,
    "httpError5xx": 2,
    "socketHangUpErrors": 1693,
    "cronjobEapis": 55712,
    "eapiDurationOver10Seconds": 738,
    "successfulOrders": 3879,
    "failedOrders": 9,
    "successfulMobilePayments": 97,
    "failedMobilePayments": 10,
    "successfulDesktopPayments": 3749,
    "failedDesktopPayments": 488,
    "successfulPaypalButFailedSubmitOrder": 4,
    "successfulPaypal": 309,
    "failedMobilePaypal": 0,
    "failedDesktopPaypal": 22,
    "openCheck": 179
  },
  {
    "date": "2025-11-15",
    "totalEapis": 196166,
    "httpErrorNon5xx": 23270,
    "httpError5xx": 0,
    "socketHangUpErrors": 1808,
    "cronjobEapis": 52203,
    "eapiDurationOver10Seconds": 662,
    "successfulOrders": 3271,
    "failedOrders": 8,
    "successfulMobilePayments": 123,
    "failedMobilePayments": 15,
    "successfulDesktopPayments": 3119,
    "failedDesktopPayments": 405,
    "successfulPaypalButFailedSubmitOrder": 4,
    "successfulPaypal": 280,
    "failedMobilePaypal": 0,
    "failedDesktopPaypal": 19,
    "openCheck": 192
  },
  {
    "date": "2025-11-16",
    "totalEapis": 167265,
    "httpErrorNon5xx": 20276,
    "httpError5xx": 0,
    "socketHangUpErrors": 1369,
    "cronjobEapis": 47909,
    "eapiDurationOver10Seconds": 529,
    "successfulOrders": 2736,
    "failedOrders": 6,
    "successfulMobilePayments": 122,
    "failedMobilePayments": 8,
    "successfulDesktopPayments": 2622,
    "failedDesktopPayments": 246,
    "successfulPaypalButFailedSubmitOrder": 1,
    "successfulPaypal": 221,
    "failedMobilePaypal": 0,
    "failedDesktopPaypal": 25,
    "openCheck": 178
  }
]